fixlib/__init__.py
fixlib/args.py
fixlib/basecategories.py
fixlib/baseplugin.py
fixlib/baseresources.py
fixlib/config.py
fixlib/durations.py
fixlib/event.py
fixlib/json.py
fixlib/json_bender.py
fixlib/jwt.py
fixlib/lock.py
fixlib/logger.py
fixlib/parse_util.py
fixlib/proc.py
fixlib/py.typed
fixlib/threading.py
fixlib/tree.py
fixlib/types.py
fixlib/units.py
fixlib/utils.py
fixlib/x509.py
fixlib/asynchronous/__init__.py
fixlib/asynchronous/stream.py
fixlib/asynchronous/utils.py
fixlib/asynchronous/web/__init__.py
fixlib/asynchronous/web/runner.py
fixlib/asynchronous/web/ws_handler.py
fixlib/core/__init__.py
fixlib/core/actions.py
fixlib/core/ca.py
fixlib/core/config.py
fixlib/core/custom_command.py
fixlib/core/events.py
fixlib/core/model_check.py
fixlib/core/model_export.py
fixlib/core/progress.py
fixlib/core/search.py
fixlib/core/tasks.py
fixlib/graph/__init__.py
fixlib/graph/graph_extensions.py
fixlib/log/__init__.py
fixlib/web/__init__.py
fixlib/web/metrics.py
fixlib/web/static/android-chrome-192x192.png
fixlib/web/static/android-chrome-512x512.png
fixlib/web/static/apple-touch-icon.png
fixlib/web/static/browserconfig.xml
fixlib/web/static/favicon-16x16.png
fixlib/web/static/favicon-32x32.png
fixlib/web/static/index.html
fixlib/web/static/mstile-150x150.png
fixlib/web/static/picnic.min.css
fixlib/web/static/site.webmanifest
fixinventorylib-4.2.0.dist-info/METADATA
fixinventorylib-4.2.0.dist-info/WHEEL
fixinventorylib-4.2.0.dist-info/top_level.txt
fixinventorylib-4.2.0.dist-info/RECORD
