Metadata-Version: 2.1
Name: fixinventorylib
Version: 4.2.0
Summary: Fix Inventory common library.
Author: Some Engineering Inc.
License: AGPLv3
Project-URL: Documentation, https://inventory.fix.security
Project-URL: Source, https://github.com/someengineering/fixinventory/tree/main/fixlib
Keywords: cloud security
Classifier: Development Status :: 5 - Production/Stable
Classifier: Intended Audience :: System Administrators
Classifier: Intended Audience :: Information Technology
Classifier: License :: OSI Approved :: GNU Affero General Public License v3 or later (AGPLv3+)
Classifier: Programming Language :: Python :: 3.12
Classifier: Operating System :: POSIX :: Linux
Classifier: Operating System :: Unix
Classifier: Environment :: Console
Classifier: Natural Language :: English
Classifier: Topic :: Security
Classifier: Topic :: Utilities
Requires-Python: >=3.12
Requires-Dist: CherryPy
Requires-Dist: Pint
Requires-Dist: PyJWT
Requires-Dist: PyYAML
Requires-Dist: aiohttp[speedups]
Requires-Dist: attrs
Requires-Dist: cattrs
Requires-Dist: cryptography
Requires-Dist: frozendict
Requires-Dist: isodate
Requires-Dist: jsons
Requires-Dist: networkx
Requires-Dist: parsy
Requires-Dist: prometheus-client
Requires-Dist: psutil
Requires-Dist: python-dateutil
Requires-Dist: pytz==2024.1
Requires-Dist: requests
Requires-Dist: typeguard
Requires-Dist: tzdata
Requires-Dist: tzlocal
Requires-Dist: websocket-client
Provides-Extra: test
Requires-Dist: black; extra == "test"
Requires-Dist: coverage; extra == "test"
Requires-Dist: flake8; extra == "test"
Requires-Dist: hypothesis; extra == "test"
Requires-Dist: mypy; extra == "test"
Requires-Dist: pep8-naming; extra == "test"
Requires-Dist: pylint; extra == "test"
Requires-Dist: pytest; extra == "test"
Requires-Dist: pytest-asyncio; extra == "test"
Requires-Dist: pytest-cov; extra == "test"
Requires-Dist: pytest-runner; extra == "test"
Requires-Dist: tox; extra == "test"
Requires-Dist: types-PyYAML; extra == "test"
Requires-Dist: types-python-dateutil; extra == "test"
Requires-Dist: types-pytz; extra == "test"
Requires-Dist: types-requests; extra == "test"
Requires-Dist: types-setuptools; extra == "test"
Requires-Dist: types-six; extra == "test"
Requires-Dist: types-tzlocal; extra == "test"
Requires-Dist: wheel; extra == "test"
